tubes/__init__.py
tubes/_components.py
tubes/_siphon.py
tubes/fan.py
tubes/framing.py
tubes/itube.py
tubes/kit.py
tubes/listening.py
tubes/memory.py
tubes/protocol.py
tubes/routing.py
tubes/tube.py
tubes/undefer.py
tubes/test/__init__.py
tubes/test/test_chatter.py
tubes/test/test_fan.py
tubes/test/test_framing.py
tubes/test/test_kit.py
tubes/test/test_listening.py
tubes/test/test_memory.py
tubes/test/test_protocol.py
tubes/test/test_routing.py
tubes/test/test_tube.py
tubes/test/test_undefer.py
tubes/test/util.py
Tubes-0.2.1.dist-info/LICENSE
Tubes-0.2.1.dist-info/METADATA
Tubes-0.2.1.dist-info/WHEEL
Tubes-0.2.1.dist-info/top_level.txt
Tubes-0.2.1.dist-info/RECORD
